pyserpZotero/.gitignore
pyserpZotero/LICENSE
pyserpZotero/__init__.py
pyserpZotero/feature_header.png
pyserpZotero/old_flash_screen.png
pyserpZotero/pyserpZotero.py
pyserpZotero/pyserpZotero_gui.py
pyserpZotero/requirements.txt
pyserpZotero/ai/__init__.py
pyserpZotero/ai/ai.py
pyserpZotero/ai/sqlite.db
pyserpZotero/minilm/README.md
pyserpZotero/minilm/config.json
pyserpZotero/minilm/config_sentence_transformers.json
pyserpZotero/minilm/model.safetensors
pyserpZotero/minilm/modules.json
pyserpZotero/minilm/sentence_bert_config.json
pyserpZotero/minilm/special_tokens_map.json
pyserpZotero/minilm/tokenizer.json
pyserpZotero/minilm/tokenizer_config.json
pyserpZotero/minilm/vocab.txt
pyserpZotero/minilm/1_Pooling/config.json
pyserpZotero/ui/colors.py
pyserpZotero/utils/__init__.py
pyserpZotero/utils/arxiv_helpers.py
pyserpZotero/utils/helpers.py
pyserpZotero/utils/pdf_downloader.py
pyserpZotero/utils/process_and_upload.py
pyserpZotero/utils/search2zotero.py
pyserpZotero/utils/search_scholar.py
pyserpzotero-1.2.0.dist-info/METADATA
pyserpzotero-1.2.0.dist-info/WHEEL
pyserpzotero-1.2.0.dist-info/entry_points.txt
pyserpzotero-1.2.0.dist-info/licenses/LICENSE
pyserpzotero-1.2.0.dist-info/RECORD
