Metadata-Version: 2.3
Name: pyserpZotero
Version: 1.2.0
Summary: Reliably scrape and clean Google Scholar citations. Automatically uploads to Zotero. Bibtex local file exports are also supported.
Project-URL: Homepage, https://github.com/hack-r/pyserpZotero
Project-URL: Bug Tracker, https://github.com/hack-r/pyserpZotero/issues
Author-email: "Miller, J." <hello@libreagora.com>
License-File: LICENSE
Classifier: License :: OSI Approved :: MIT License
Classifier: Operating System :: OS Independent
Classifier: Programming Language :: Python :: 3
Requires-Python: >=3.7
